jwt_generator
