Metadata-Version: 1.0
Name: jwt-generator
Version: 0.9.0
Summary: unix command line JWT generator.
Home-page: https://github.com/mvanholsteijn/jwt-generator
Author: Mark van Holsteijn
Author-email: mvanholsteijn@xebia.com
License: UNKNOWN
Platform: any
